{
	"artistId": 243100,
	"albumTitle": "<뜻밖의 만남> 여덟 번째",
	"releaseDate": "2017-03-15",
	"trackTitle": "나무",
	"discNumber": 1,
	"trackNumber": 1,
	"trackId": 16658546,
	"lyric": {
		"timeIndex": [
			[0.5, 3.9],
			[4.8, 14.6],
			[15, 17.8],
			[18.8, 18.1],
			[30.1, 34.6],
			[35.5, 42.2],
			[42.7, 46.7],
			[47.3, 46.5],
			[57.5, 61.3],
			[62.5, 61.9],
			[73.5, 77.8],
			[78.1, 88],
			[116.1, 120.3],
			[120.6, 127.2],
			[127.8, 136.8],
			[137.4, 140.9],
			[141.9, 147],
			[151.8, 154.5],
			[154.9, 157.3],
			[157.8, 165.4],
			[166.9, 171.2],
			[172.3, 179.1],
			[179.4, 182.9],
			[183.4, 187.2],
			[188.2, 190.8],
			[191.8, 195.9],
			[197.3, 199.6],
			[200.8, 209.9]
		],
		"text": "난 그의 손을 만질 때\n그의 날들을 꽤 오래 엿보았지\n깊게 패인 손금에\n모른 척해 온 외로움이 숨어있었고\n이렇게 거칠었는 줄\n다시금 알았네\n그의 얼굴을 마주할 때\n그의 어린 날들을 비춰보았지\n떨어뜨린 입가에 한가득\n지나간 시절을 머금고 있었고\n낡고 오래된 기억을\n여전히 견디고 있었네\n낡고 오래된 기억을\n여전히 견디우며\n눈물 말리고 있었네\n난 그의 주름살처럼\n메마른 것을 본 적 단 한 번 없지\n나를 힘겹게 안고\n고요히 눈을 감기에\n슬피 우는 법을 잊은 줄 알았고\n이렇게 바람 부는 줄\n나는 몰랐네\n꽃 맺음이 다 한\n굽은 등줄기는\n초라했지만\n그가 떠난 자리는\n나무랄 곳 없이\n텅 비어있게 했다"
	}
}
