{
	"artistId": 15649,
	"albumTitle": "Supersonic",
	"releaseDate": "2012-07-03",
	"trackTitle": "Supersonic",
	"discNumber": 1,
	"trackNumber": 1,
	"trackId": 3253560,
	"lyric": {
		"timeIndex": [
			[24.8, 35.8],
			[38.5, 52.3],
			[66, 79.1],
			[79.7, 90.7],
			[91.7, 98.3],
			[98.6, 104.7],
			[105.4, 112],
			[113.9, 127.2],
			[138, 150.7],
			[151.7, 164.8],
			[165.4, 176.4],
			[177.4, 184],
			[184.3, 190.3],
			[191.2, 197.8],
			[199.6, 212.1],
			[234, 240.1],
			[240.7, 246.9],
			[247.7, 253.8],
			[254.6, 260.7],
			[261.4, 268],
			[268.2, 284.1]
		],
		"text": "조금만기다려늦진않았을테니Cuz I say\n쓰러진기억이나를세워줄테니Cuz I say\n조금만기다려너를데려갈테니그대로있어줘\n이젠끝났어지겨운아픔도이젠알겠어내가누구인지\nSupersonic, through your heartbeat 가슴터질듯한 Pressure\n타오르길끝도없이너에게로달려가\nSupersonic, no more wasting다시찾아온 Eruption\n눈을떠, 네앞에서있어\n조금만기다려너를데려갈테니Cuz I'm here\n새로운시간이너와함께할테니그대로있어줘\n다시찾았어잊었던꿈들을이젠알겠어내가누구인지\nSupersonic, through your heartbeat 가슴터질듯한 Pressure\n타오르길끝도없이너에게로달려가\nSupersonic, no more wasting다시찾아온 Eruption\n눈을떠, 네앞에서있어\n불안했던기다림더는없을거라고 Anyway\n너의곁에있을게네가느낄수있게\nSupersonic, through your heartbeat 가슴터질듯한 Pressure\n타오르길끝도없이너에게로달려가\nSupersonic, no more wasting다시찾아온 Eruption\n눈을떠, 니앞에서있어"
	}
}
