{
	"artistId": 15649,
	"albumTitle": "Just Listen",
	"releaseDate": "2013-05-02",
	"trackTitle": "Just Listen (Feat. SKULL)",
	"discNumber": 1,
	"trackNumber": 1,
	"trackId": 3794003,
	"lyric": {
		"timeIndex": [
			[32.6, 36.4],
			[37.4, 39.8],
			[40, 42.1],
			[42.9, 46.7],
			[47.7, 49.9],
			[50.3, 52],
			[52.9, 55.2],
			[55.5, 57.7],
			[58, 60.9],
			[62.2, 64.1],
			[64.8, 67.1],
			[67.4, 69.7],
			[70.1, 72.3],
			[73.5, 75.4],
			[76.1, 78],
			[78.7, 83],
			[83.9, 85.7],
			[86.4, 88.2],
			[89.7, 93.3],
			[101.3, 103.3],
			[103.5, 106.1],
			[106.3, 108.8],
			[108.5, 111.2],
			[111.5, 113.8],
			[113.6, 116.1],
			[116.6, 118.7],
			[118.5, 121.3],
			[121.6, 124],
			[124.5, 129.1],
			[129.7, 134.3],
			[134.8, 139.6],
			[140, 144.4],
			[145.8, 147.4],
			[148.3, 150.2],
			[150.9, 155.4],
			[156.1, 157.9],
			[158.6, 160.5],
			[161.3, 165.7],
			[172.7, 172.3],
			[173, 175.7],
			[176.1, 180.3],
			[181.2, 186.2],
			[187.1, 189],
			[189.7, 191.6],
			[192.2, 196.5],
			[197.4, 199.2],
			[200, 201.8],
			[203.2, 206.9]
		],
		"text": "문을 열어둘게 언제든 들어와도 돼\n취해 볼래 진한 깊이에\n아무것도 필요없어\n문을 열어둘게 언제든 들어와도 돼\n맡겨 줄래 너를 나에게\n단지 몸만 오면 돼\n쌓여온 history and mistery\n그냥 너랑 나 우리\n맡겨줄래 단지 너를 나에게\n난 모난 예술가 아니고\n웃음에 능하지 않지만\n위로가 돼 줄 수 있지 난\n지친 너를 안아 줄 수 있지 난\n쇼를 보여줄 순 없지만\n소릴 들려줄 수 있지 난\n나를 찾는 너 내가 자신감이 돼 줄게\n쇼를 보여줄 순 없지만\n소릴 들려줄 수 있지 난\n내 길을 가는 내게 자신감이 돼 줄래\nI man don't want nothing from you\n외로울때면 내가 항상 너의 옆에 My gyal\n달콤한 모닝 키스 you so fine gyal\n하나 밖에 모르는 type 그게 나인걸\n너밖에 모르는 아이 그게 나인걸\n의심따위는 필요없어 ragga muffin\n스타일은 처음부터 ragga muffin\nparaiso dominica 나와 멋진\n나와 멋진 랄랄라\nwhy yoyoyo 내게 모든 걸 맡겨봐요\nwhy yoyoyo 이제 내 소리 들어봐요\nwhy yoyoyo 내게 모든 걸 말해봐요\nwhy yo why yo 랄랄라\n쇼를 보여줄 순 없지만\n소릴 들려줄 수 있지 난\n나를 찾는 너 내가 자신감이 돼 줄게\n쇼를 보여줄 순 없지만\n소릴 들려줄 수 있지 난\n내 길을 가는 내게 자신감이 돼 줄래\nwhy yoyoyo 내게 모든 걸 맡겨봐요\nwhy yoyoyo 이제 내 소리 들어봐요\nwhy yoyoyo 내게 모든 걸 말해봐요\nwhy yo why yo 랄랄라\n쇼를 보여줄 순 없지만\n소릴 들려줄 수 있지 난\n나를 찾는 너 내가 자신감이 돼 줄게\n쇼를 보여줄 순 없지만\n소릴 들려줄 수 있지 난\n내 길을 가는 내게 자신감이 돼 줄래"
	}
}
