{
	"artistId": 15649,
	"albumTitle": "없어",
	"releaseDate": "2014-01-03",
	"trackTitle": "없어 (Studio Live Ver.)",
	"discNumber": 1,
	"trackNumber": 1,
	"trackId": 4056080,
	"lyric": {
		"timeIndex": [
			[1.7, 8.7],
			[9.5, 24.5],
			[33.9, 40.7],
			[41.3, 55.9],
			[56.3, 63.9],
			[64.4, 71.4],
			[72.6, 80],
			[80.4, 96.3],
			[97.3, 103.6],
			[104.1, 121.6],
			[127.1, 134.7],
			[135.2, 142.7],
			[143.3, 150.2],
			[151.2, 159.4],
			[161, 168.6],
			[168.9, 185.4]
		],
		"text": "바람은 불어 창밖에 있지만\n너와 나 사이를 시리도록 베고 가네 차갑게\n스쳐가겠지 오래 걸리지 않아\n또 지나가겠지 우리가 사랑을 버린 것처럼\n다 똑같은 얘기 지루하던 매일 서로를 지워가는 이유\n너는 다르겠지 처음 기대와는 달리 또 다시 익숙한 이별 하나\n사랑해 느낌이 없어 미안해 진심이 없어\n고마워 감정이 없어 그만해 계속할 필요 없어\n잊혀지겠지 작은 추억만 남아\n널 잊어 가겠지 사랑이 우리를 버린 것처럼\n다 똑같은 얘기 지루하던 매일 서로를 지워가는 이유\n너는 다르겠지 처음 기대와는 달리 또 다시 익숙한 이별 하나\n노래는 흘러 들리진 않지만\n침묵 속 너와 나 익숙하게 떠나보내네\n사랑해 느낌이 없어 미안해 진심이 없어\n고마워 감정이 없어 그만해 계속할 필요 없어"
	}
}
