{
	"artistId": 243100,
	"albumTitle": "AKMU [항해] TOUR LIVE",
	"releaseDate": "2020-07-03",
	"trackTitle": "물 만난 물고기",
	"discNumber": 1,
	"trackNumber": 1,
	"trackId": 40669035,
	"lyric": {
		"timeIndex": [
			[18.5, 23.2],
			[38.7, 43.2],
			[43.8, 47.5],
			[48.2, 52.7],
			[53.6, 59],
			[61.3, 65.8],
			[66.2, 70.2],
			[70.8, 74.9],
			[75.3, 82.4],
			[83.3, 85.3],
			[85.7, 87.7],
			[88.1, 91.5],
			[93.4, 97.7],
			[99, 100.4],
			[101, 102.9],
			[103.2, 106.5],
			[107.6, 111.4],
			[112.4, 116.6],
			[117.1, 123.2],
			[140.9, 145.4],
			[145.9, 149.9],
			[150.4, 155.1],
			[154.9, 161.8],
			[162.9, 165],
			[165.4, 167.4],
			[167.9, 171.1],
			[172.4, 174],
			[174.8, 180.5],
			[182.5, 186.1],
			[186.9, 190.9],
			[192, 196.2],
			[196.7, 199.8],
			[201.7, 205.1],
			[206.3, 209.9],
			[211, 214.5],
			[215.7, 218.4],
			[218.8, 224.3],
			[228.2, 235.4]
		],
		"text": "(출항)\n한바탕 휩쓸고 간 폭풍의 잔해 속에\n언제 그랬냐는 듯 잔잔한 파도\n비치는 내 얼굴 울렁이는 내 얼굴\n너는 바다가 되고 난 배가 되었네\n고독함이 머무는 파란 도화지 속에\n죽음이 어색할 만큼 찬란한 빛깔들\n날아가는 생명들 헤엄치는 생명들\n너는 물감이 되고 난 붓이 되었네\n너는 꼭 살아서\n지푸라기라도 잡아서\n내 이름을 기억해줘\n음악을 잘했던 외로움을 좋아했던\n바다의 한마디\n우리가 노래하듯이\n우리가 노래하듯이\n우리가 말하듯이\n우리가 헤엄치듯이 살길\nLIVE LIKE THE WAY WE SING\n한바탕 휩쓸고 간 폭풍의 잔해 속에\n덩그러니 남겨진 마지막 작품\n독백의 순간을 버티고야 비로소\n너는 예술이 되고 또 전설이 되었네\n너는 꼭 살아서\n죽기 살기로 살아서\n내가 있었음을 음악 해줘\n그는 동경했던\n기어코 물을 만나서 물고기처럼 떠나야 했네\n우리가 노래하듯이\n우리가 말하듯이\n우리가 예언하듯이 살길\nLIVE LIKE THE WAY WE SING\n우리가 노래하듯이\n우리가 말하듯이\n우리가 예언하듯이 살길\nLIVE LIKE THE WAY WE SING\n(같이 불러요)\n(더 크게)"
	}
}
