{
	"artistId": 15649,
	"albumTitle": "YOUNHA 6th Album 'END THEORY'",
	"releaseDate": "2021-11-16",
	"trackTitle": "잘 지내",
	"discNumber": 1,
	"trackNumber": 5,
	"trackId": 51781048,
	"lyric": {
		"timeIndex": [
			[24.5, 26.1],
			[27.6, 32.1],
			[33.6, 37],
			[39.3, 43.4],
			[44, 48.2],
			[48.6, 51.2],
			[51.6, 56],
			[57.6, 62],
			[63.3, 67.6],
			[72.6, 75.2],
			[75.7, 79.2],
			[80.6, 83.3],
			[84.8, 86.9],
			[87.6, 92.5],
			[92.9, 95],
			[96.6, 99.3],
			[99.6, 102.4],
			[102.6, 106.4],
			[106.9, 108.3],
			[109.2, 112.6],
			[113, 115.5],
			[116, 119.7],
			[120.7, 123.1],
			[123.7, 125.8],
			[126.7, 130.4],
			[131, 132.2],
			[133.2, 136.7],
			[136.9, 139],
			[140, 144.3],
			[168.6, 171.4],
			[171.6, 174.5],
			[174.6, 178.4],
			[178.9, 180.4],
			[181.2, 184.6],
			[185, 187.6],
			[188, 191.7],
			[192.6, 195.3],
			[195.7, 197.8],
			[198.7, 202.4],
			[203, 204.2],
			[205.2, 208.6],
			[208.9, 211],
			[212, 215.4],
			[216.7, 219.2],
			[219.8, 223.2],
			[224.6, 226.3],
			[228.8, 230.9],
			[231.6, 235.4],
			[237, 240.9]
		],
		"text": "뭐랄까,\n구름이 걷히고 운이 좋으면\n투명한 조각의 무지개처럼\n떠올라 볼 수 있었어\n그 때 우리를\n인연은\n우연히도 다가와 떠나가고\n노력할수록 상처가 되어서\n이런 내가 됐지만\n마음에 마음을 가누려 애를쓰던\n아이를 안아줄 어른이 되었다는게\n자랑스러워\n가끔은 좀 막막해도 견디고\n내일을 위해 잠이 들 줄 알아\n이젠 울지 않거든\nHow U doing\n잘 지내, 그랬으면 해\n실수였던 말들에\n아프지 말고\n돌아갈 수 없어도\n기억하고 있어\n마음 깊은 곳에 있어\nWhere're U going\n지금쯤 함께였다면\n좋았겠다 생각해\n그래도 어떤\n이유가 있을거야\n모쪼록 난 좋아\n너도 잘 지냈으면 해\nHow U doing\n잘 지내, 그랬으면 해\n실수였던 말들에\n아프지 말고\n돌아갈 수 없어도\n기억하고 있어\n마음 깊은 곳에 있어\nWhere're U going\n지금쯤 함께였다면\n좋았겠다 생각해\n그래도 어떤\n이유가 있을거야\n모쪼록 난 좋아\n너도 잘 지냈으면 해\n마음에 마음을 가누려 애를쓰던\n아이를 안아줄 어른이 되었다는게\n자랑스러워\n가끔은 좀 막막해도 견디고\n내일을 위해 잠이 들 줄 알아\n이젠 울지 않거든"
	}
}
