{
	"artistId": 15649,
	"albumTitle": "View",
	"releaseDate": "2015-10-14",
	"trackTitle": "星よりも遠い人 / Hoshiyorimo Toi Hito (별보다도 먼 사람)",
	"discNumber": 1,
	"trackNumber": 2,
	"trackId": 5761639,
	"lyric": {
		"timeIndex": [
			[0, null],
			[15, null],
			[22, null],
			[29, null],
			[32, null],
			[42, null],
			[45, null],
			[52, null],
			[59, null],
			[66, null],
			[73, null],
			[80, null],
			[86, null],
			[94, null],
			[102, null],
			[108, null],
			[114, null],
			[120, null],
			[128, null],
			[134, null],
			[139, null],
			[161, null],
			[167, null],
			[174, null],
			[177, null],
			[185, null],
			[191, null],
			[199, null],
			[204, null],
			[215, null],
			[223, null],
			[230, null],
			[233, null],
			[242, null],
			[249, null],
			[256, null],
			[281, null],
			[289, null],
			[296, null],
			[304, null],
			[308, null],
			[315, null],
			[322, null],
			[333, null]
		],
		"text": "星よりも遠い人 / Hoshiyorimo Toi Hito (별보다도 먼 사람) - 윤하\n私の前で　誰かのこと\nそんな風に見つめないで\n言えるわけない\nあなたの恋人じゃないから\nたった一行の\nなんでもないメールだけで\nあなたのこと笑顔にする\nその人になれたらいいのに\n通り過ぎてく恋人たち\nどうして心が通じたんだろう\n会いたい　会いたい\nただ伝えたいだけなのに\nねえ、できないこと 叶わぬこと\n何もないと思ってたんだ\n星空さえ手を伸ばせば\nつかめると信じていたんだ\nねえ、愛してます 愛してます\nその指先ふれてみたい\n恋しいあなたは\n星よりも遠い人\n優しい言葉くれた夜は\n思いだして抱きしめてる\nたとえそれが\n特別じゃないとわかってても\nあなたのことしか考えない\n長い１日が終わってゆくの\n会いたい 会いたい\n心は不自由すぎて\nねえ、できないこと 叶わぬこと\n何もないと思ってたんだ\nあなたにさえ\n出あわなければこんなに苦しくなかったの\nねえ、愛してます 愛してます\nもっとそばで見つめていたい\n恋しいあなたは星よりも遠い人\nねえ、できないこと 叶わぬこと\n何もないと思ってたんだ\n星空さえ手を伸ばせばつかめると\n信じていたんだ\nねえ、愛してます 愛してます\nその指先ふれてみたい\n恋しいあなたは　星よりも遠い人\n星よりも遠い人"
	}
}
